[
  {
    "archived_at": "2026-04-13T08:37:19.720955+00:00",
    "compressed_bytes": 11209925,
    "date": "2026-04-13",
    "object_count": 67052,
    "provenance": "genesis_from_gp",
    "query_strategy": "current_gp_genesis",
    "sha256": "8db001c11d1161c7c253919fffbe00e0830429446fdb5fd9a1d861cef7229656",
    "state_as_of_utc": "2026-04-13T08:37:06Z"
  },
  {
    "archived_at": "2026-04-14T07:31:46.396512+00:00",
    "compressed_bytes": 11234782,
    "date": "2026-04-14",
    "object_count": 67052,
    "previous_sha256": "6d8add7eb501a4f00be5f46d8a7c2665ea87d5c97c2a0e313fd9d14005b7d680",
    "provenance": "genesis_from_gp",
    "query_strategy": "current_gp_genesis",
    "regenerated_at": "2026-04-14T07:31:46.397311+00:00",
    "sha256": "9aed7fe45e2d748548fc063e73da3bde7105276b99c6ad511d3c55d0d21c4cd3",
    "state_as_of_utc": "2026-04-14T07:31:34Z"
  }
]
